baker/__init__.py
baker/bparser.py
baker/chatbot.py
baker/trainer.py
baker_python-2.0.dist-info/METADATA
baker_python-2.0.dist-info/WHEEL
baker_python-2.0.dist-info/top_level.txt
baker_python-2.0.dist-info/RECORD
