Metadata-Version: 2.1
Name: baker-python
Version: 2.0
Summary: A framework to create chatbots in the easiest way
Home-page: https://github.com/enginestein/Baker
Author: Arya Praneil Pritesh
Author-email: aryapraneil@gmail.com
License: GPL-3.0-only
Project-URL: Source, https://github.com/enginestein/Baker
Project-URL: Tracker, https://github.com/enginestein/Baker
Classifier: Development Status :: 5 - Production/Stable
Classifier: Programming Language :: Python :: 3 :: Only
Classifier: Programming Language :: Python :: 3
Classifier: Programming Language :: Python :: 3.6
Classifier: Programming Language :: Python :: 3.7
Classifier: Programming Language :: Python :: 3.8
Classifier: Programming Language :: Python :: 3.9
Classifier: Programming Language :: Python :: 3.10
Classifier: Environment :: Console
Classifier: Intended Audience :: Developers
Classifier: Natural Language :: English
Classifier: Operating System :: OS Independent
